mediapack/__init__.py
mediapack/air.py
mediapack/elastic.py
mediapack/eqf.py
mediapack/fluid.py
mediapack/medium.py
mediapack/pem.py
mediapack/screen.py
mediapack/utils/__init__.py
mediapack/utils/from_yaml.py
tests/__init__.py
tests/test_loading.py
mediapack-0.3.0.dist-info/METADATA
mediapack-0.3.0.dist-info/WHEEL
mediapack-0.3.0.dist-info/top_level.txt
mediapack-0.3.0.dist-info/RECORD
