Metadata-Version: 2.1
Name: mediapack
Version: 0.3.0
Summary: Media repository for acoustics
Home-page: https://github.com/cpplanes/mediapack
Author: O. Dazel, Mathieu (matael) Gaborit
Author-email: gaborit@kth.se
License: MIT
Platform: UNKNOWN
Classifier: Programming Language :: Python :: 3
Classifier: Operating System :: OS Independent
Requires-Dist: numpy (>=1.13.1)
Requires-Dist: PyYAML (>=5.1)
